CHANGES.txt
LICENSE.txt
MANIFEST.in
README.txt
setup.py
src/p01/__init__.py
src/p01.sampledata.egg-info/PKG-INFO
src/p01.sampledata.egg-info/SOURCES.txt
src/p01.sampledata.egg-info/dependency_links.txt
src/p01.sampledata.egg-info/namespace_packages.txt
src/p01.sampledata.egg-info/not-zip-safe
src/p01.sampledata.egg-info/requires.txt
src/p01.sampledata.egg-info/top_level.txt
src/p01/sampledata/README.txt
src/p01/sampledata/__init__.py
src/p01/sampledata/generator.py
src/p01/sampledata/interfaces.py
src/p01/sampledata/loremipsum.txt
src/p01/sampledata/phrase.txt
src/p01/sampledata/tests.py
src/p01/sampledata/topics.txt
src/p01/sampledata/util.py
src/p01/sampledata/words.txt